{"url":"https://www.youtube.com/watch?v=6Hi6VMCr-jk","picks":[{"source":"MMA JAWN","domain":"mma","pick":"Ty Miller","opponent":"Adam Fugette","directness":"explicit","confidence":1,"quote":"I'm gonna go with Ty Miller to win by decision","timestamp":"2026-01-19T17:36:41Z","url":"https://www.youtube.com/watch?v=6Hi6VMCr-jk"},{"source":"MMA JAWN","domain":"mma","pick":"Cameron Smotherman","opponent":"Ricky Torsos","directness":"explicit","confidence":0.7,"quote":"I'm going to go ahead and pick Came Smotherin","timestamp":"2026-01-19T17:36:41Z","url":"https://www.youtube.com/watch?v=6Hi6VMCr-jk"},{"source":"MMA JAWN","domain":"mma","pick":"Josh Hookit","opponent":"Denzel Freeman","directness":"explicit","confidence":0.9,"quote":"I think I got Josh Hokit for a first or second round knockout","timestamp":"2026-01-19T17:36:41Z","url":"https://www.youtube.com/watch?v=6Hi6VMCr-jk"},{"source":"MMA JAWN","domain":"mma","pick":"Alexander Hernandez","opponent":"Michael Johnson","directness":"explicit","confidence":0.8,"quote":"I'm going to go with Alexander Hernandez","timestamp":"2026-01-19T17:36:41Z","url":"https://www.youtube.com/watch?v=6Hi6VMCr-jk"},{"source":"MMA JAWN","domain":"mma","pick":"Alex Perez","opponent":"Charles Johnson","directness":"implicit","confidence":0.7,"quote":"I'm going to go ahead and lean Alex Perez","timestamp":"2026-01-19T17:36:41Z","url":"https://www.youtube.com/watch?v=6Hi6VMCr-jk"},{"source":"MMA JAWN","domain":"mma","pick":"Mudesus Bukovskis","opponent":"Nikita Krill","directness":"explicit","confidence":0.7,"quote":"I do think Modessus here gets this win","timestamp":"2026-01-19T17:36:41Z","url":"https://www.youtube.com/watch?v=6Hi6VMCr-jk"},{"source":"MMA JAWN","domain":"mma","pick":"Abba Gatier","opponent":"Andre Pulv","directness":"explicit","confidence":1,"quote":"we're going to go with a tip of Katiier to get it done by knockout","timestamp":"2026-01-19T17:36:41Z","url":"https://www.youtube.com/watch?v=6Hi6VMCr-jk"},{"source":"MMA JAWN","domain":"mma","pick":"Umar Numagra Madov","opponent":"Davidson Figuero","directness":"explicit","confidence":1,"quote":"Umar Magov should definitely get it done and with ease","timestamp":"2026-01-19T17:36:41Z","url":"https://www.youtube.com/watch?v=6Hi6VMCr-jk"},{"source":"MMA JAWN","domain":"mma","pick":"Jean Silva","opponent":"Arnold Allen","directness":"explicit","confidence":0.9,"quote":"Jing Silva to win by knockout or decision","timestamp":"2026-01-19T17:36:41Z","url":"https://www.youtube.com/watch?v=6Hi6VMCr-jk"},{"source":"MMA JAWN","domain":"mma","pick":"Natalyia Silva","opponent":"Rose Namunes","directness":"explicit","confidence":0.8,"quote":"I'm going to go ahead and say Natalyia Silva wins by decision","timestamp":"2026-01-19T17:36:41Z","url":"https://www.youtube.com/watch?v=6Hi6VMCr-jk"},{"source":"MMA JAWN","domain":"mma","pick":"Wilder Cortez A Costa","opponent":"Derrick Lewis","directness":"explicit","confidence":0.9,"quote":"I'm going to go ahead and pick Wilder Cortez A Costa","timestamp":"2026-01-19T17:36:41Z","url":"https://www.youtube.com/watch?v=6Hi6VMCr-jk"},{"source":"MMA JAWN","domain":"mma","pick":"Shawn Omali","opponent":"Sona Dong","directness":"explicit","confidence":0.9,"quote":"I got Shawn Ali to win this pretty easily","timestamp":"2026-01-19T17:36:41Z","url":"https://www.youtube.com/watch?v=6Hi6VMCr-jk"},{"source":"MMA JAWN","domain":"mma","pick":"Justin Gatei","opponent":"Patty Pimpblelet","directness":"explicit","confidence":0.7,"quote":"I'm taking the dog here. Justin Gate to win by knockout","timestamp":"2026-01-19T17:36:41Z","url":"https://www.youtube.com/watch?v=6Hi6VMCr-jk"}],"fp":"87b51dbb1d25","at":"2026-07-15T17:19:07.026Z"}