{"url":"https://www.youtube.com/watch?v=6pdg9zr06wM","picks":[{"source":"MMA EXPERTS","domain":"mma","pick":"Abdulaev","opponent":"Jefferson Nascimento","directness":"explicit","confidence":0.6,"quote":"I got to lean towards Abdulaev. So, I'll pick him to pull it off.","timestamp":"2026-06-23T04:42:37Z","url":"https://www.youtube.com/watch?v=6pdg9zr06wM"},{"source":"MMA EXPERTS","domain":"mma","pick":"Nascimento","opponent":"Abdulaev","directness":"implicit","confidence":0.7,"quote":"I just think Nascimento's better, bro.","timestamp":"2026-06-23T04:42:37Z","url":"https://www.youtube.com/watch?v=6pdg9zr06wM"},{"source":"MMA EXPERTS","domain":"mma","pick":"Bekzat Almakhan","opponent":"John Maksumoto","directness":"explicit","confidence":0.9,"quote":"I'll favor Al Matkhan with the boxing and wrestling edge.","timestamp":"2026-06-23T04:42:37Z","url":"https://www.youtube.com/watch?v=6pdg9zr06wM"},{"source":"MMA EXPERTS","domain":"mma","pick":"Danil Donchenko","opponent":"Feodor Bergren","directness":"explicit","confidence":0.9,"quote":"Donchenko KO. Easy call.","timestamp":"2026-06-23T04:42:37Z","url":"https://www.youtube.com/watch?v=6pdg9zr06wM"},{"source":"MMA EXPERTS","domain":"mma","pick":"Khan O'Fally","opponent":"Javier Reyes","directness":"implicit","confidence":0.7,"quote":"I am not going to pick Reyes... Give me him [O'Fally]","timestamp":"2026-06-23T04:42:37Z","url":"https://www.youtube.com/watch?v=6pdg9zr06wM"},{"source":"MMA EXPERTS","domain":"mma","pick":"Javier Reyes","opponent":"Khan O'Fally","directness":"explicit","confidence":0.6,"quote":"I'm going the minus 160 favorite in Javyer Reyes.","timestamp":"2026-06-23T04:42:37Z","url":"https://www.youtube.com/watch?v=6pdg9zr06wM"},{"source":"MMA EXPERTS","domain":"mma","pick":"Rizvan Kuniev","opponent":"Sultan Aliev","directness":"explicit","confidence":0.8,"quote":"I'll go Rizvan Boev to take it.","timestamp":"2026-06-23T04:42:37Z","url":"https://www.youtube.com/watch?v=6pdg9zr06wM"},{"source":"MMA EXPERTS","domain":"mma","pick":"Nursultan Ruziboev","opponent":"Andre Pulyaev","directness":"explicit","confidence":0.9,"quote":"We'll pick him [Ruziboev] to get it.","timestamp":"2026-06-23T04:42:37Z","url":"https://www.youtube.com/watch?v=6pdg9zr06wM"},{"source":"MMA EXPERTS","domain":"mma","pick":"Abdul-Rakhman Yakubov","opponent":"Julius Walker","directness":"explicit","confidence":0.9,"quote":"Yakhyaev inside the distance is the pick.","timestamp":"2026-06-23T04:42:37Z","url":"https://www.youtube.com/watch?v=6pdg9zr06wM"},{"source":"MMA EXPERTS","domain":"mma","pick":"Eric Noland","opponent":"Farman Khasanov","directness":"explicit","confidence":0.6,"quote":"I'm going Nolan by KO.","timestamp":"2026-06-23T04:42:37Z","url":"https://www.youtube.com/watch?v=6pdg9zr06wM"},{"source":"MMA EXPERTS","domain":"mma","pick":"Farman Khasanov","opponent":"Eric Noland","directness":"explicit","confidence":0.7,"quote":"Give me Assanov... Assanov's finishing Nolan.","timestamp":"2026-06-23T04:42:37Z","url":"https://www.youtube.com/watch?v=6pdg9zr06wM"},{"source":"MMA EXPERTS","domain":"mma","pick":"Mykola Oleksiychuk","opponent":"Abu Magomedov","directness":"explicit","confidence":0.9,"quote":"MYKOLA OLEKSIYCHUK via knockout, baby.","timestamp":"2026-06-23T04:42:37Z","url":"https://www.youtube.com/watch?v=6pdg9zr06wM"},{"source":"MMA EXPERTS","domain":"mma","pick":"Bruno Ferreira","opponent":"Ikram Aliskerov","directness":"explicit","confidence":0.6,"quote":"I'm going Bruno Ferreira by a knockout.","timestamp":"2026-06-23T04:42:37Z","url":"https://www.youtube.com/watch?v=6pdg9zr06wM"},{"source":"MMA EXPERTS","domain":"mma","pick":"Ikram Aliskerov","opponent":"Bruno Ferreira","directness":"explicit","confidence":0.8,"quote":"Ikram Aliskerov TKO.","timestamp":"2026-06-23T04:42:37Z","url":"https://www.youtube.com/watch?v=6pdg9zr06wM"},{"source":"MMA EXPERTS","domain":"mma","pick":"Asu Almabayev","opponent":"Charles Johnson","directness":"explicit","confidence":0.8,"quote":"Almabayev decision with you, bro.","timestamp":"2026-06-23T04:42:37Z","url":"https://www.youtube.com/watch?v=6pdg9zr06wM"},{"source":"MMA EXPERTS","domain":"mma","pick":"Nazim Sadykhov","opponent":"Matheus Camilo","directness":"explicit","confidence":0.9,"quote":"We're going Sadykhov for the W.","timestamp":"2026-06-23T04:42:37Z","url":"https://www.youtube.com/watch?v=6pdg9zr06wM"},{"source":"MMA EXPERTS","domain":"mma","pick":"Shara Bullet Magomedov","opponent":"Michel Pereira","directness":"explicit","confidence":0.9,"quote":"I'm going KO for this eye of none other than the king Shara Bullet.","timestamp":"2026-06-23T04:42:37Z","url":"https://www.youtube.com/watch?v=6pdg9zr06wM"},{"source":"MMA EXPERTS","domain":"mma","pick":"Manel Torres","opponent":"Rafael Fiziev","directness":"explicit","confidence":0.9,"quote":"Manel Torres to beat Fiziev here.","timestamp":"2026-06-23T04:42:37Z","url":"https://www.youtube.com/watch?v=6pdg9zr06wM"}],"fp":"87b51dbb1d25","at":"2026-07-15T05:11:57.785Z"}