{"url":"https://www.youtube.com/watch?v=DdboltEcLR4","picks":[{"source":"DFS BY THE NUMBERS","domain":"mma","pick":"Melissa Mullins","opponent":"Claudia Siga","directness":"explicit","confidence":0.9,"quote":"I think Mullen actually goes out there and pays off this price tag","timestamp":"2024-11-09T03:23:13Z","url":"https://www.youtube.com/watch?v=DdboltEcLR4"},{"source":"DFS BY THE NUMBERS","domain":"mma","pick":"Tresean Gore","opponent":"Antonio Trocoli","directness":"implicit","confidence":0.6,"quote":"if I was forced to bet it it would be on Gore","timestamp":"2024-11-09T03:23:13Z","url":"https://www.youtube.com/watch?v=DdboltEcLR4"},{"source":"DFS BY THE NUMBERS","domain":"mma","pick":"Theon Blackshear","opponent":"Cody Stamann","directness":"implicit","confidence":0.7,"quote":"I do slightly black Shire","timestamp":"2024-11-09T03:23:13Z","url":"https://www.youtube.com/watch?v=DdboltEcLR4"},{"source":"DFS BY THE NUMBERS","domain":"mma","pick":"Charles Radtke","opponent":"Matthew Semelsberger","directness":"explicit","confidence":0.8,"quote":"I have a half unit shot on racky by submission","timestamp":"2024-11-09T03:23:13Z","url":"https://www.youtube.com/watch?v=DdboltEcLR4"},{"source":"DFS BY THE NUMBERS","domain":"mma","pick":"Elizeu Zaleski dos Santos","opponent":"Zack Scrogin","directness":"explicit","confidence":0.9,"quote":"I think zeleski wins this fight","timestamp":"2024-11-09T03:23:13Z","url":"https://www.youtube.com/watch?v=DdboltEcLR4"},{"source":"DFS BY THE NUMBERS","domain":"mma","pick":"Denise Gomes","opponent":"Karolina Kowalkiewicz","directness":"implicit","confidence":0.7,"quote":"I lean decision","timestamp":"2024-11-09T03:23:13Z","url":"https://www.youtube.com/watch?v=DdboltEcLR4"},{"source":"DFS BY THE NUMBERS","domain":"mma","pick":"Manuer Abdul Malik","opponent":"Dusko Todorovic","directness":"explicit","confidence":0.9,"quote":"I think Abdul Malik probably does go out there get this fight down to the mat and and pound dusa head in","timestamp":"2024-11-09T03:23:13Z","url":"https://www.youtube.com/watch?v=DdboltEcLR4"},{"source":"DFS BY THE NUMBERS","domain":"mma","pick":"Jillian Robertson","opponent":"Luana Pinheiro","directness":"explicit","confidence":0.9,"quote":"I like Robertson as pretty much everybody does","timestamp":"2024-11-09T03:23:13Z","url":"https://www.youtube.com/watch?v=DdboltEcLR4"},{"source":"DFS BY THE NUMBERS","domain":"mma","pick":"Cavius Ramus","opponent":"Gaston Bolanos","directness":"explicit","confidence":0.8,"quote":"I got Rus here inside the distance","timestamp":"2024-11-09T03:23:13Z","url":"https://www.youtube.com/watch?v=DdboltEcLR4"},{"source":"DFS BY THE NUMBERS","domain":"mma","pick":"Mirsad Bektic","opponent":"Reinier de Ridder","directness":"implicit","confidence":0.6,"quote":"I've cashed many uh mirart two3 props... and especially here","timestamp":"2024-11-09T03:23:13Z","url":"https://www.youtube.com/watch?v=DdboltEcLR4"},{"source":"DFS BY THE NUMBERS","domain":"mma","pick":"Carlos Prates","opponent":"Neil Magny","directness":"implicit","confidence":0.8,"quote":"press should win","timestamp":"2024-11-09T03:23:13Z","url":"https://www.youtube.com/watch?v=DdboltEcLR4"}],"fp":"87b51dbb1d25","at":"2026-07-15T21:47:28.256Z"}