{"url":"https://www.youtube.com/watch?v=e_gKIXF9XxY","picks":[{"source":"LucasTracyMMA","domain":"mma","pick":"Quillin Sal","opponent":"Yanal Ashmuse","directness":"explicit","confidence":0.6,"quote":"I'm going to lean Quillin Saul killed.","timestamp":"2025-06-01T17:00:20Z","url":"https://www.youtube.com/watch?v=e_gKIXF9XxY"},{"source":"LucasTracyMMA","domain":"mma","pick":"Juang Yo","opponent":"Ja Sari","directness":"explicit","confidence":1,"quote":"I'm picking Juice saying, 'Yo, I don't need He's undefeated.'","timestamp":"2025-06-01T17:00:20Z","url":"https://www.youtube.com/watch?v=e_gKIXF9XxY"},{"source":"LucasTracyMMA","domain":"mma","pick":"Wang Kong","opponent":"Arian Dilva","directness":"explicit","confidence":0.7,"quote":"I ended up picking Wang Kong.","timestamp":"2025-06-01T17:00:20Z","url":"https://www.youtube.com/watch?v=e_gKIXF9XxY"},{"source":"LucasTracyMMA","domain":"mma","pick":"Chaos Williams","opponent":"Andreas Gusson","directness":"explicit","confidence":0.6,"quote":"I'm gonna go with Chaos Williams to win this by decision.","timestamp":"2025-06-01T17:00:20Z","url":"https://www.youtube.com/watch?v=e_gKIXF9XxY"},{"source":"LucasTracyMMA","domain":"mma","pick":"Sergi Spivac","opponent":"Waldo Cortez Aosta","directness":"explicit","confidence":0.9,"quote":"I'm gonna go with Sergi Spitback by a first or second round submission","timestamp":"2025-06-01T17:00:20Z","url":"https://www.youtube.com/watch?v=e_gKIXF9XxY"},{"source":"LucasTracyMMA","domain":"mma","pick":"Azimat Mzakonov","opponent":"Brendesen Ribero","directness":"explicit","confidence":1,"quote":"I have no doubt in my mind that Azimconov is going to knock Brendan Rivero out bad","timestamp":"2025-06-01T17:00:20Z","url":"https://www.youtube.com/watch?v=e_gKIXF9XxY"},{"source":"LucasTracyMMA","domain":"mma","pick":"Joshua Van","opponent":"Bruno Silva","directness":"explicit","confidence":0.8,"quote":"Joshua Van should get this one done by decision.","timestamp":"2025-06-01T17:00:20Z","url":"https://www.youtube.com/watch?v=e_gKIXF9XxY"},{"source":"LucasTracyMMA","domain":"mma","pick":"Vicente Lu","opponent":"Kevin Holland","directness":"explicit","confidence":0.8,"quote":"I'm picking Vicente Luc.","timestamp":"2025-06-01T17:00:20Z","url":"https://www.youtube.com/watch?v=e_gKIXF9XxY"},{"source":"LucasTracyMMA","domain":"mma","pick":"Mario Batista","opponent":"Patchy Mix","directness":"explicit","confidence":0.7,"quote":"I'm going with Mario Batista.","timestamp":"2025-06-01T17:00:20Z","url":"https://www.youtube.com/watch?v=e_gKIXF9XxY"},{"source":"LucasTracyMMA","domain":"mma","pick":"Joe Pyer","opponent":"Kelvin Gastelum","directness":"explicit","confidence":0.9,"quote":"I'm going to go with Joe Piper by KO.","timestamp":"2025-06-01T17:00:20Z","url":"https://www.youtube.com/watch?v=e_gKIXF9XxY"},{"source":"LucasTracyMMA","domain":"mma","pick":"Juliana Pñena","opponent":"Kayla Harrison","directness":"explicit","confidence":0.6,"quote":"I'm picking Juliana Pñena, man.","timestamp":"2025-06-01T17:00:20Z","url":"https://www.youtube.com/watch?v=e_gKIXF9XxY"},{"source":"LucasTracyMMA","domain":"mma","pick":"Morab Deval Vely","opponent":"Shawn Ali","directness":"explicit","confidence":0.8,"quote":"I'm going with Morab winning.","timestamp":"2025-06-01T17:00:20Z","url":"https://www.youtube.com/watch?v=e_gKIXF9XxY"}],"fp":"87b51dbb1d25","at":"2026-07-15T16:53:51.832Z"}