{"url":"https://www.youtube.com/watch?v=JPS5_cloWVo","picks":[{"source":"The Mike Finch Show","domain":"mma","pick":"Francis Ngannou","opponent":"Felipe Lins","directness":"explicit","confidence":0.9,"quote":"I'm picking Francis.","timestamp":"2026-05-16T19:02:15Z","url":"https://www.youtube.com/watch?v=JPS5_cloWVo"},{"source":"The Mike Finch Show","domain":"mma","pick":"Niccole Callari","opponent":"Shauna Bannon","directness":"implicit","confidence":0.7,"quote":"I'm going to lean Niccole Callari.","timestamp":"2026-05-16T19:02:15Z","url":"https://www.youtube.com/watch?v=JPS5_cloWVo"},{"source":"The Mike Finch Show","domain":"mma","pick":"Danielle Barres","opponent":"Luis Gurule","directness":"explicit","confidence":0.8,"quote":"I'm going Danielle Barres.","timestamp":"2026-05-16T19:02:15Z","url":"https://www.youtube.com/watch?v=JPS5_cloWVo"},{"source":"The Mike Finch Show","domain":"mma","pick":"Alice Ardelion","opponent":"Polyana Viana","directness":"explicit","confidence":0.8,"quote":"I like Ardelion here.","timestamp":"2026-05-16T19:02:15Z","url":"https://www.youtube.com/watch?v=JPS5_cloWVo"},{"source":"The Mike Finch Show","domain":"mma","pick":"Andre Petroski","opponent":"Cody Brundage","directness":"implicit","confidence":0.7,"quote":"I got to lean Petroski in this one.","timestamp":"2026-05-16T19:02:15Z","url":"https://www.youtube.com/watch?v=JPS5_cloWVo"},{"source":"The Mike Finch Show","domain":"mma","pick":"Raquel Pennington","opponent":"Ketlen Vieira","directness":"explicit","confidence":0.8,"quote":"Raquel Pennington on the cards.","timestamp":"2026-05-16T19:02:15Z","url":"https://www.youtube.com/watch?v=JPS5_cloWVo"},{"source":"The Mike Finch Show","domain":"mma","pick":"Arthur Miniev","opponent":"Tommy Gantt","directness":"explicit","confidence":0.9,"quote":"Gane's a lock.","timestamp":"2026-05-16T19:02:15Z","url":"https://www.youtube.com/watch?v=JPS5_cloWVo"},{"source":"The Mike Finch Show","domain":"mma","pick":"Tuco Tokos","opponent":"Ivan Erslan","directness":"explicit","confidence":0.9,"quote":"I think that he's going to be able to submit Ivan Erslan, too.","timestamp":"2026-05-16T19:02:15Z","url":"https://www.youtube.com/watch?v=JPS5_cloWVo"},{"source":"The Mike Finch Show","domain":"mma","pick":"Nikolay Veretennikov","opponent":"Khaos Williams","directness":"explicit","confidence":0.9,"quote":"Verhoeven's a lock.","timestamp":"2026-05-16T19:02:15Z","url":"https://www.youtube.com/watch?v=JPS5_cloWVo"},{"source":"The Mike Finch Show","domain":"mma","pick":"Bernardo Sopai","opponent":"Timmy Kuamba","directness":"explicit","confidence":0.8,"quote":"I think Bernardo Sopai is going to do what he wants to this dude.","timestamp":"2026-05-16T19:02:15Z","url":"https://www.youtube.com/watch?v=JPS5_cloWVo"},{"source":"The Mike Finch Show","domain":"mma","pick":"Modestas Bukauskas","opponent":"Christian Edwards","directness":"explicit","confidence":0.9,"quote":"He's probably a lock against Christian Edwards.","timestamp":"2026-05-16T19:02:15Z","url":"https://www.youtube.com/watch?v=JPS5_cloWVo"},{"source":"The Mike Finch Show","domain":"mma","pick":"Malcolm Wellmaker","opponent":"Juan Diaz","directness":"explicit","confidence":0.8,"quote":"I think Malcolm Wellmaker should be able to get it done here.","timestamp":"2026-05-16T19:02:15Z","url":"https://www.youtube.com/watch?v=JPS5_cloWVo"},{"source":"The Mike Finch Show","domain":"mma","pick":"Doo Ho Choi","opponent":"Daniel Santos","directness":"explicit","confidence":0.7,"quote":"I'm going to go with Doo Ho Choi, man.","timestamp":"2026-05-16T19:02:15Z","url":"https://www.youtube.com/watch?v=JPS5_cloWVo"},{"source":"The Mike Finch Show","domain":"mma","pick":"Melquizael Costa","opponent":"Arnold Allen","directness":"explicit","confidence":0.8,"quote":"I'm going to take the in-season Melquizael Costa over Arnold Allen.","timestamp":"2026-05-16T19:02:15Z","url":"https://www.youtube.com/watch?v=JPS5_cloWVo"},{"source":"The Mike Finch Show","domain":"mma","pick":"Ronda Rousey","opponent":"Gina Carano","directness":"explicit","confidence":0.9,"quote":"It's Ronda Rousey over Gina Carano first round armbar.","timestamp":"2026-05-16T19:02:15Z","url":"https://www.youtube.com/watch?v=JPS5_cloWVo"},{"source":"The Mike Finch Show","domain":"mma","pick":"Mike Perry","opponent":"Nate Diaz","directness":"explicit","confidence":0.8,"quote":"I got Mike Perry, all right?","timestamp":"2026-05-16T19:02:15Z","url":"https://www.youtube.com/watch?v=JPS5_cloWVo"},{"source":"The Mike Finch Show","domain":"mma","pick":"Saladin Parnasse","opponent":"Kenny Cross","directness":"explicit","confidence":0.8,"quote":"I think he's going to be able to get a finish over Kenny Cross.","timestamp":"2026-05-16T19:02:15Z","url":"https://www.youtube.com/watch?v=JPS5_cloWVo"},{"source":"The Mike Finch Show","domain":"mma","pick":"Robelis Despaigne","opponent":"Junior dos Santos","directness":"explicit","confidence":0.7,"quote":"I ain't pick flipping. Robelis Despaigne.","timestamp":"2026-05-16T19:02:15Z","url":"https://www.youtube.com/watch?v=JPS5_cloWVo"},{"source":"The Mike Finch Show","domain":"mma","pick":"Nam Phan","opponent":"Jake Babyan","directness":"explicit","confidence":0.7,"quote":"I have to pick him with my head.","timestamp":"2026-05-16T19:02:15Z","url":"https://www.youtube.com/watch?v=JPS5_cloWVo"},{"source":"The Mike Finch Show","domain":"mma","pick":"Eileen Pereira","opponent":"Jade Masson Wong","directness":"implicit","confidence":0.7,"quote":"I lean Pereira over Jade Masson Wong.","timestamp":"2026-05-16T19:02:15Z","url":"https://www.youtube.com/watch?v=JPS5_cloWVo"}],"fp":"87b51dbb1d25","at":"2026-07-15T16:34:00.457Z"}