{"url":"https://www.youtube.com/watch?v=Kh5Kj08srDs","picks":[{"source":"Sean Brady (SteadyPicks)","domain":"mma","pick":"Tim Means","opponent":"Court McGee","directness":"explicit","confidence":0.9,"quote":"I'm going with the dodo bird... I'm probably going to go dirty bird as well","timestamp":"2024-10-04T16:10:05Z","url":"https://www.youtube.com/watch?v=Kh5Kj08srDs"},{"source":"Sean Brady (SteadyPicks)","domain":"mma","pick":"Tisha Pennington","opponent":"Carla Esparza","directness":"explicit","confidence":0.8,"quote":"I'm going to go with the opposition... I'm going to go with Tisha Pennington","timestamp":"2024-10-04T16:10:05Z","url":"https://www.youtube.com/watch?v=Kh5Kj08srDs"},{"source":"Sean Brady (SteadyPicks)","domain":"mma","pick":"Ryan Spann","opponent":"Ovince Saint Preux","directness":"explicit","confidence":0.9,"quote":"I am going with Ryan span by knockout","timestamp":"2024-10-04T16:10:05Z","url":"https://www.youtube.com/watch?v=Kh5Kj08srDs"},{"source":"Sean Brady (SteadyPicks)","domain":"mma","pick":"Ihor Potieria","opponent":"Cesar Almeida","directness":"explicit","confidence":0.8,"quote":"I'm going with ehor man","timestamp":"2024-10-04T16:10:05Z","url":"https://www.youtube.com/watch?v=Kh5Kj08srDs"},{"source":"Sean Brady (SteadyPicks)","domain":"mma","pick":"Hernandez","opponent":"Hubbert","directness":"explicit","confidence":0.7,"quote":"I think I would have to go Hernandez","timestamp":"2024-10-04T16:10:05Z","url":"https://www.youtube.com/watch?v=Kh5Kj08srDs"},{"source":"Sean Brady (SteadyPicks)","domain":"mma","pick":"Lando","opponent":"Marina Rodriguez","directness":"implicit","confidence":0.6,"quote":"I think I'm going to go lendo honestly","timestamp":"2024-10-04T16:10:05Z","url":"https://www.youtube.com/watch?v=Kh5Kj08srDs"},{"source":"Sean Brady (SteadyPicks)","domain":"mma","pick":"Joaquin Buckley","opponent":"Stephen Thompson","directness":"explicit","confidence":0.9,"quote":"I'm picking Buckley","timestamp":"2024-10-04T16:10:05Z","url":"https://www.youtube.com/watch?v=Kh5Kj08srDs"},{"source":"Sean Brady (SteadyPicks)","domain":"mma","pick":"Kayla Harrison","opponent":"Ketlen Vieira","directness":"explicit","confidence":1,"quote":"Kayla Harrison put anybody in there she's the next women's champ","timestamp":"2024-10-04T16:10:05Z","url":"https://www.youtube.com/watch?v=Kh5Kj08srDs"},{"source":"Sean Brady (SteadyPicks)","domain":"mma","pick":"Roman Dolidze","opponent":"Kevin Holland","directness":"explicit","confidence":0.8,"quote":"I'm picking Roman money line","timestamp":"2024-10-04T16:10:05Z","url":"https://www.youtube.com/watch?v=Kh5Kj08srDs"},{"source":"Sean Brady (SteadyPicks)","domain":"mma","pick":"Jose Aldo","opponent":"Mario Bautista","directness":"explicit","confidence":1,"quote":"Jose Aldo by whatever the [__] he wants","timestamp":"2024-10-04T16:10:05Z","url":"https://www.youtube.com/watch?v=Kh5Kj08srDs"},{"source":"Sean Brady (SteadyPicks)","domain":"mma","pick":"Raquel Pennington","opponent":"Juliana Pena","directness":"explicit","confidence":0.9,"quote":"I'm going to go Pennington","timestamp":"2024-10-04T16:10:05Z","url":"https://www.youtube.com/watch?v=Kh5Kj08srDs"}],"fp":"87b51dbb1d25","at":"2026-07-15T16:11:38.181Z"}