{"url":"https://www.youtube.com/watch?v=KHcqYszfLSk","picks":[{"source":"Morning Kombat","domain":"mma","pick":"Steve Garcia","opponent":"David Onama","directness":"explicit","confidence":0.8,"quote":"I'm calling Steve Garcia by decision","timestamp":"2025-10-31T17:15:36Z","url":"https://www.youtube.com/watch?v=KHcqYszfLSk"},{"source":"Morning Kombat","domain":"mma","pick":"Ante Delija","opponent":"Waldo Cortes da Costa","directness":"explicit","confidence":0.9,"quote":"I'm going to pick Ante Delia","timestamp":"2025-10-31T17:15:36Z","url":"https://www.youtube.com/watch?v=KHcqYszfLSk"}],"fp":"87b51dbb1d25","at":"2026-07-15T18:14:33.246Z"}