{"url":"https://www.youtube.com/watch?v=mmsFFKWhL0c","picks":[{"source":"Santino DeFranco","domain":"mma","pick":"Tai Miller","opponent":"Adam Fugit","directness":"explicit","confidence":0.8,"quote":"I think it's going to be Tai by decision.","timestamp":"2026-01-20T13:01:35Z","url":"https://www.youtube.com/watch?v=mmsFFKWhL0c"},{"source":"Santino DeFranco","domain":"mma","pick":"Cameron Smotherman","opponent":"Ricky Tersios","directness":"explicit","confidence":0.9,"quote":"I like Smotherman here. Um, and I think he's gonna I think he's gonna put a beating on Tricios.","timestamp":"2026-01-20T13:01:35Z","url":"https://www.youtube.com/watch?v=mmsFFKWhL0c"},{"source":"Santino DeFranco","domain":"mma","pick":"Josh Hokit","opponent":"Denzel Freeman","directness":"explicit","confidence":0.7,"quote":"I will pick Hulk. It's a win","timestamp":"2026-01-20T13:01:35Z","url":"https://www.youtube.com/watch?v=mmsFFKWhL0c"},{"source":"Santino DeFranco","domain":"mma","pick":"Alex Perez","opponent":"Charles Johnson","directness":"explicit","confidence":0.7,"quote":"I like Perez here. I think the value you can't beat.","timestamp":"2026-01-20T13:01:35Z","url":"https://www.youtube.com/watch?v=mmsFFKWhL0c"},{"source":"Santino DeFranco","domain":"mma","pick":"Modestus Bukascus","opponent":"Nikita Krylov","directness":"explicit","confidence":0.8,"quote":"I like Modestas here and I don't like run the tape back. I don't think I've ever said a good thing about this.","timestamp":"2026-01-20T13:01:35Z","url":"https://www.youtube.com/watch?v=mmsFFKWhL0c"},{"source":"Santino DeFranco","domain":"mma","pick":"Aba Galier","opponent":"Andre Pulv","directness":"explicit","confidence":0.9,"quote":"He's the man. He's going to he's going to crush him.","timestamp":"2026-01-20T13:01:35Z","url":"https://www.youtube.com/watch?v=mmsFFKWhL0c"},{"source":"Santino DeFranco","domain":"mma","pick":"Umar Nurmagamedov","opponent":"Davidson Figuredo","directness":"explicit","confidence":0.9,"quote":"I think Umar wins um probably second or third round submission.","timestamp":"2026-01-20T13:01:35Z","url":"https://www.youtube.com/watch?v=mmsFFKWhL0c"},{"source":"Santino DeFranco","domain":"mma","pick":"Jean Silva","opponent":"Arnold Allen","directness":"explicit","confidence":0.8,"quote":"I think Silva is one of the best fighters in the world right now. Um, I think he beats Allen.","timestamp":"2026-01-20T13:01:35Z","url":"https://www.youtube.com/watch?v=mmsFFKWhL0c"},{"source":"Santino DeFranco","domain":"mma","pick":"Natalyia Silva","opponent":"Rose Namayunes","directness":"explicit","confidence":0.9,"quote":"give me Natalyia Silva every freaking day of the week here.","timestamp":"2026-01-20T13:01:35Z","url":"https://www.youtube.com/watch?v=mmsFFKWhL0c"},{"source":"Santino DeFranco","domain":"mma","pick":"Waldo Cortez Aosta","opponent":"Derrick Lewis","directness":"explicit","confidence":0.6,"quote":"I think it's going to be a Waldo knockout.","timestamp":"2026-01-20T13:01:35Z","url":"https://www.youtube.com/watch?v=mmsFFKWhL0c"},{"source":"Santino DeFranco","domain":"mma","pick":"Sean O'Malley","opponent":"Yong Song","directness":"explicit","confidence":0.6,"quote":"I think Shawn wins it.","timestamp":"2026-01-20T13:01:35Z","url":"https://www.youtube.com/watch?v=mmsFFKWhL0c"},{"source":"Santino DeFranco","domain":"mma","pick":"Justin Gachi","opponent":"Patty Pimblelet","directness":"explicit","confidence":0.7,"quote":"I'm gonna go Gachi, too. I think he's way better.","timestamp":"2026-01-20T13:01:35Z","url":"https://www.youtube.com/watch?v=mmsFFKWhL0c"}],"fp":"87b51dbb1d25","at":"2026-07-15T17:34:23.051Z"}