{"url":"https://www.youtube.com/watch?v=mqjmLDyUo_4","picks":[{"source":"DFS BY THE NUMBERS","domain":"mma","pick":"Eduarda Moura","opponent":"Veronica Hardy","directness":"explicit","confidence":0.8,"quote":"give me the underdog here in Edward Mar to win this fight by decision","timestamp":"2024-11-14T02:05:00Z","url":"https://www.youtube.com/watch?v=mqjmLDyUo_4"},{"source":"DFS BY THE NUMBERS","domain":"mma","pick":"Oban Elliott","opponent":"Basil Hafez","directness":"explicit","confidence":0.7,"quote":"I'll take Elliot to win a decision","timestamp":"2024-11-14T02:05:00Z","url":"https://www.youtube.com/watch?v=mqjmLDyUo_4"},{"source":"DFS BY THE NUMBERS","domain":"mma","pick":"Mickey Gall","opponent":"Ramiz Brahimaj","directness":"explicit","confidence":0.6,"quote":"I like Mickey G to win this fight probably by decision","timestamp":"2024-11-14T02:05:00Z","url":"https://www.youtube.com/watch?v=mqjmLDyUo_4"},{"source":"DFS BY THE NUMBERS","domain":"mma","pick":"Marcin Tybura","opponent":"Jhonata Diniz","directness":"implicit","confidence":0.7,"quote":"I do got a lean with tyur here","timestamp":"2024-11-14T02:05:00Z","url":"https://www.youtube.com/watch?v=mqjmLDyUo_4"},{"source":"DFS BY THE NUMBERS","domain":"mma","pick":"David Onama","opponent":"Roberto Romero","directness":"explicit","confidence":0.9,"quote":"give me a David onama to win this fight","timestamp":"2024-11-14T02:05:00Z","url":"https://www.youtube.com/watch?v=mqjmLDyUo_4"},{"source":"DFS BY THE NUMBERS","domain":"mma","pick":"Jim Miller","opponent":"Damon Jackson","directness":"explicit","confidence":0.7,"quote":"I'll take Jim Miller to win this fight by second round knockout","timestamp":"2024-11-14T02:05:00Z","url":"https://www.youtube.com/watch?v=mqjmLDyUo_4"},{"source":"DFS BY THE NUMBERS","domain":"mma","pick":"Eric Anders","opponent":"Chris Weidman","directness":"explicit","confidence":0.7,"quote":"I'm taking Anders to win this fight","timestamp":"2024-11-14T02:05:00Z","url":"https://www.youtube.com/watch?v=mqjmLDyUo_4"},{"source":"DFS BY THE NUMBERS","domain":"mma","pick":"Marcus McGhee","opponent":"Jonathan Martinez","directness":"explicit","confidence":0.8,"quote":"I like Marcus McGee here I'll take him to win this fight by knockout","timestamp":"2024-11-14T02:05:00Z","url":"https://www.youtube.com/watch?v=mqjmLDyUo_4"},{"source":"DFS BY THE NUMBERS","domain":"mma","pick":"Mauricio Ruffy","opponent":"James Llontop","directness":"explicit","confidence":0.9,"quote":"I'll take huy to win this fight by third round knockout","timestamp":"2024-11-14T02:05:00Z","url":"https://www.youtube.com/watch?v=mqjmLDyUo_4"},{"source":"DFS BY THE NUMBERS","domain":"mma","pick":"Karine Silva","opponent":"Viviane Araujo","directness":"explicit","confidence":0.7,"quote":"I'll take Silva to win this fight and I'll take her to win this fight by decision","timestamp":"2024-11-14T02:05:00Z","url":"https://www.youtube.com/watch?v=mqjmLDyUo_4"},{"source":"DFS BY THE NUMBERS","domain":"mma","pick":"Bo Nickal","opponent":"Paul Craig","directness":"explicit","confidence":0.9,"quote":"I like b nickel here I think he wins this fight by first round knockout","timestamp":"2024-11-14T02:05:00Z","url":"https://www.youtube.com/watch?v=mqjmLDyUo_4"},{"source":"DFS BY THE NUMBERS","domain":"mma","pick":"Charles Oliveira","opponent":"Michael Chandler","directness":"explicit","confidence":0.8,"quote":"I like Charles here... I think he's going to submit Michael Chandler in the second round","timestamp":"2024-11-14T02:05:00Z","url":"https://www.youtube.com/watch?v=mqjmLDyUo_4"},{"source":"DFS BY THE NUMBERS","domain":"mma","pick":"Jon Jones","opponent":"Stipe Miocic","directness":"explicit","confidence":0.9,"quote":"give me Jon Jones here to win this fight by decision","timestamp":"2024-11-14T02:05:00Z","url":"https://www.youtube.com/watch?v=mqjmLDyUo_4"}],"fp":"87b51dbb1d25","at":"2026-07-15T23:48:50.184Z"}