{"url":"https://www.youtube.com/watch?v=pi-xgFhYyK0","picks":[{"source":"Tim Welch","domain":"mma","pick":"Magomed Ankalaev","opponent":"Aleksandar Rakic","directness":"explicit","confidence":0.9,"quote":"so I'm picking maged anv by KO","timestamp":"2024-10-24T19:07:44Z","url":"https://www.youtube.com/watch?v=pi-xgFhYyK0"},{"source":"Tim Welch","domain":"mma","pick":"Robert Whittaker","opponent":"Hamzat Chimaev","directness":"explicit","confidence":0.7,"quote":"I can see Robert Whitaker possibly getting a TKO in that fourth or fifth round","timestamp":"2024-10-24T19:07:44Z","url":"https://www.youtube.com/watch?v=pi-xgFhYyK0"},{"source":"Tim Welch","domain":"mma","pick":"Max Holloway","opponent":"Ilia Topuria","directness":"explicit","confidence":0.8,"quote":"if I'm picking right now I'm picking Max Holloway gets it done by decision","timestamp":"2024-10-24T19:07:44Z","url":"https://www.youtube.com/watch?v=pi-xgFhYyK0"}],"fp":"87b51dbb1d25","at":"2026-07-15T04:47:31.161Z"}