{"url":"https://www.youtube.com/watch?v=PP-GNBQYfCI","picks":[{"source":"We Want Picks","domain":"mma","pick":"Bobby Green","opponent":"Lance Gibson Jr.","directness":"explicit","confidence":0.9,"quote":"Bobb's going to be the pick.","timestamp":"2025-12-10T04:15:53Z","url":"https://www.youtube.com/watch?v=PP-GNBQYfCI"},{"source":"We Want Picks","domain":"mma","pick":"Theresa Blade","opponent":"Jamie Lynn Horth","directness":"explicit","confidence":0.6,"quote":"I'm going to pick bladed here.","timestamp":"2025-12-10T04:15:53Z","url":"https://www.youtube.com/watch?v=PP-GNBQYfCI"},{"source":"We Want Picks","domain":"mma","pick":"Allan AJ Fry","opponent":"Guierme Pat","directness":"explicit","confidence":0.7,"quote":"I'll take the more athletic guy... He's the pick.","timestamp":"2025-12-10T04:15:53Z","url":"https://www.youtube.com/watch?v=PP-GNBQYfCI"},{"source":"We Want Picks","domain":"mma","pick":"Melissa Croin","opponent":"Lana Santos","directness":"explicit","confidence":0.8,"quote":"I think Melissa wins. I bet on Melissa.","timestamp":"2025-12-10T04:15:53Z","url":"https://www.youtube.com/watch?v=PP-GNBQYfCI"},{"source":"We Want Picks","domain":"mma","pick":"Steven Aspund","opponent":"Shawn Sharff","directness":"explicit","confidence":0.7,"quote":"I have to pick Steven Aspen here though, literally because of the cardio.","timestamp":"2025-12-10T04:15:53Z","url":"https://www.youtube.com/watch?v=PP-GNBQYfCI"},{"source":"We Want Picks","domain":"mma","pick":"Yarislava Amisov","opponent":"Neil Magny","directness":"explicit","confidence":0.8,"quote":"Yarsov is the pick.","timestamp":"2025-12-10T04:15:53Z","url":"https://www.youtube.com/watch?v=PP-GNBQYfCI"},{"source":"We Want Picks","domain":"mma","pick":"Jillian Robertson","opponent":"Amanda Lamosh","directness":"explicit","confidence":0.7,"quote":"Jillian Robertson's going to be the pick.","timestamp":"2025-12-10T04:15:53Z","url":"https://www.youtube.com/watch?v=PP-GNBQYfCI"},{"source":"We Want Picks","domain":"mma","pick":"Marcus Betta","opponent":"Kennedy and Chuck Woo","directness":"explicit","confidence":0.6,"quote":"I'm going to pick the guy that's going to move forward... I picked Marcus Bucheta","timestamp":"2025-12-10T04:15:53Z","url":"https://www.youtube.com/watch?v=PP-GNBQYfCI"},{"source":"We Want Picks","domain":"mma","pick":"Morgan Sherriier","opponent":"Mel Costa","directness":"explicit","confidence":0.9,"quote":"Morgan is the pick.","timestamp":"2025-12-10T04:15:53Z","url":"https://www.youtube.com/watch?v=PP-GNBQYfCI"},{"source":"We Want Picks","domain":"mma","pick":"Cesari Oletach","opponent":"Caesar Almeida","directness":"explicit","confidence":0.7,"quote":"I'm picking Cesari.","timestamp":"2025-12-10T04:15:53Z","url":"https://www.youtube.com/watch?v=PP-GNBQYfCI"},{"source":"We Want Picks","domain":"mma","pick":"Giga Chicad","opponent":"Kevin Vallejo","directness":"explicit","confidence":0.6,"quote":"I'm picking Giga Chicad.","timestamp":"2025-12-10T04:15:53Z","url":"https://www.youtube.com/watch?v=PP-GNBQYfCI"},{"source":"We Want Picks","domain":"mma","pick":"Manell Cop","opponent":"Brandon Roy Val","directness":"explicit","confidence":0.7,"quote":"I'm going to pick Minnell Cop.","timestamp":"2025-12-10T04:15:53Z","url":"https://www.youtube.com/watch?v=PP-GNBQYfCI"}],"fp":"87b51dbb1d25","at":"2026-07-15T16:17:39.286Z"}