{"url":"https://www.youtube.com/watch?v=rSu1avdxYV0","picks":[{"source":"DFS BY THE NUMBERS","domain":"mma","pick":"Julia Polastri","opponent":"Zaleha Alateng Cole","directness":"explicit","confidence":0.9,"quote":"I like Polastri here.","timestamp":"2026-04-25T15:14:50Z","url":"https://www.youtube.com/watch?v=rSu1avdxYV0"},{"source":"DFS BY THE NUMBERS","domain":"mma","pick":"Victor Valenzuela","opponent":"Max Griffin","directness":"implicit","confidence":0.6,"quote":"I lean Valenzuela","timestamp":"2026-04-25T15:14:50Z","url":"https://www.youtube.com/watch?v=rSu1avdxYV0"},{"source":"DFS BY THE NUMBERS","domain":"mma","pick":"Francis Marshall","opponent":"Lucas Brennan","directness":"explicit","confidence":0.9,"quote":"I think Marshall rolls here.","timestamp":"2026-04-25T15:14:50Z","url":"https://www.youtube.com/watch?v=rSu1avdxYV0"},{"source":"DFS BY THE NUMBERS","domain":"mma","pick":"Jafel Filho","opponent":"Cody Durden","directness":"explicit","confidence":0.9,"quote":"I think it's Filio.","timestamp":"2026-04-25T15:14:50Z","url":"https://www.youtube.com/watch?v=rSu1avdxYV0"},{"source":"DFS BY THE NUMBERS","domain":"mma","pick":"Michelle Waterson","opponent":"Mariya Agapova","directness":"explicit","confidence":0.9,"quote":"I think Waterson absolutely destroys Mariya Agapova.","timestamp":"2026-04-25T15:14:50Z","url":"https://www.youtube.com/watch?v=rSu1avdxYV0"},{"source":"DFS BY THE NUMBERS","domain":"mma","pick":"Jacks McVay","opponent":"Sedriques Dumas","directness":"explicit","confidence":0.8,"quote":"I like McVay... a decent amount actually.","timestamp":"2026-04-25T15:14:50Z","url":"https://www.youtube.com/watch?v=rSu1avdxYV0"},{"source":"DFS BY THE NUMBERS","domain":"mma","pick":"Rodolfo Vieira","opponent":"Eric McConnel","directness":"explicit","confidence":0.9,"quote":"Vieira should absolutely win this fight.","timestamp":"2026-04-25T15:14:50Z","url":"https://www.youtube.com/watch?v=rSu1avdxYV0"},{"source":"DFS BY THE NUMBERS","domain":"mma","pick":"Marcos Rogerio","opponent":"Ryan Spann","directness":"explicit","confidence":0.8,"quote":"I think Rogerio should win this one.","timestamp":"2026-04-25T15:14:50Z","url":"https://www.youtube.com/watch?v=rSu1avdxYV0"},{"source":"DFS BY THE NUMBERS","domain":"mma","pick":"Montel Jackson","opponent":"Raoni Barcelos","directness":"explicit","confidence":0.8,"quote":"I think Jackson's very likely to knock out Barcelos.","timestamp":"2026-04-25T15:14:50Z","url":"https://www.youtube.com/watch?v=rSu1avdxYV0"},{"source":"DFS BY THE NUMBERS","domain":"mma","pick":"Davey Grant","opponent":"Adrian Yanez Martinelli","directness":"implicit","confidence":0.6,"quote":"I lean his way.","timestamp":"2026-04-25T15:14:50Z","url":"https://www.youtube.com/watch?v=rSu1avdxYV0"},{"source":"DFS BY THE NUMBERS","domain":"mma","pick":"Rafa Garcia","opponent":"Hernandez","directness":"implicit","confidence":0.5,"quote":"I ever so slightly lean Garcia","timestamp":"2026-04-25T15:14:50Z","url":"https://www.youtube.com/watch?v=rSu1avdxYV0"},{"source":"DFS BY THE NUMBERS","domain":"mma","pick":"Norma Dumont","opponent":"Jourdain Everts","directness":"implicit","confidence":0.6,"quote":"I lean Dumont.","timestamp":"2026-04-25T15:14:50Z","url":"https://www.youtube.com/watch?v=rSu1avdxYV0"},{"source":"DFS BY THE NUMBERS","domain":"mma","pick":"Youssef Zalal","opponent":"Aljamain Sterling","directness":"implicit","confidence":0.5,"quote":"I lean Zalal here over the course of five rounds.","timestamp":"2026-04-25T15:14:50Z","url":"https://www.youtube.com/watch?v=rSu1avdxYV0"}],"fp":"87b51dbb1d25","at":"2026-07-16T03:58:26.329Z"}