{"url":"https://www.youtube.com/watch?v=T919vescT1o","picks":[{"source":"Winning In The Shadows","domain":"mma","pick":"Tai Miller","opponent":"Adam Fugit","directness":"explicit","confidence":0.9,"quote":"I expect Tai Miller to win.","timestamp":"2026-01-22T02:58:19Z","url":"https://www.youtube.com/watch?v=T919vescT1o"},{"source":"Winning In The Shadows","domain":"mma","pick":"Cameron Smotherman","opponent":"Ricky Tersios","directness":"explicit","confidence":0.9,"quote":"the pick is Smotherman.","timestamp":"2026-01-22T02:58:19Z","url":"https://www.youtube.com/watch?v=T919vescT1o"},{"source":"Winning In The Shadows","domain":"mma","pick":"Josh Hokit","opponent":"Denzel Freeman","directness":"explicit","confidence":0.9,"quote":"I got Hulk hit in a landslide.","timestamp":"2026-01-22T02:58:19Z","url":"https://www.youtube.com/watch?v=T919vescT1o"},{"source":"Winning In The Shadows","domain":"mma","pick":"Alexander Hernandez","opponent":"Michael Johnson","directness":"explicit","confidence":0.7,"quote":"It's Hernandez as the official pick for this video.","timestamp":"2026-01-22T02:58:19Z","url":"https://www.youtube.com/watch?v=T919vescT1o"},{"source":"Winning In The Shadows","domain":"mma","pick":"Charles Johnson","opponent":"Alex Perez","directness":"explicit","confidence":0.8,"quote":"Love Charles Johnson on the money line.","timestamp":"2026-01-22T02:58:19Z","url":"https://www.youtube.com/watch?v=T919vescT1o"},{"source":"Winning In The Shadows","domain":"mma","pick":"Modestas Bukauskas","opponent":"Nikita Krylov","directness":"explicit","confidence":0.9,"quote":"I've got Bukowskis winning this one.","timestamp":"2026-01-22T02:58:19Z","url":"https://www.youtube.com/watch?v=T919vescT1o"},{"source":"Winning In The Shadows","domain":"mma","pick":"Tabatha Ricci","opponent":"Plev","directness":"explicit","confidence":0.9,"quote":"To me, this is a showcase from Godier. I don't see a world in which he doesn't absolutely spark pulley.","timestamp":"2026-01-22T02:58:19Z","url":"https://www.youtube.com/watch?v=T919vescT1o"},{"source":"Winning In The Shadows","domain":"mma","pick":"Umar Nurmagomedov","opponent":"Deiveson Figueiredo","directness":"explicit","confidence":0.9,"quote":"I think he's going to do it this week.","timestamp":"2026-01-22T02:58:19Z","url":"https://www.youtube.com/watch?v=T919vescT1o"},{"source":"Winning In The Shadows","domain":"mma","pick":"Natalia Silva","opponent":"Rose Namajunas","directness":"explicit","confidence":0.9,"quote":"she'll be the easy pick for me.","timestamp":"2026-01-22T02:58:19Z","url":"https://www.youtube.com/watch?v=T919vescT1o"},{"source":"Winning In The Shadows","domain":"mma","pick":"Derrick Lewis","opponent":"Waldo Cortes-Acosta","directness":"explicit","confidence":0.8,"quote":"I will take Derrick Lewis as the underdog.","timestamp":"2026-01-22T02:58:19Z","url":"https://www.youtube.com/watch?v=T919vescT1o"},{"source":"Winning In The Shadows","domain":"mma","pick":"Yadong Song","opponent":"Sean O'Malley","directness":"explicit","confidence":0.8,"quote":"Sonia Dong's going to be the pick here.","timestamp":"2026-01-22T02:58:19Z","url":"https://www.youtube.com/watch?v=T919vescT1o"},{"source":"Winning In The Shadows","domain":"mma","pick":"Paddy Pimblett","opponent":"Justin Gaethje","directness":"explicit","confidence":0.7,"quote":"Give me Patty Pimpblelet. Give me Pably Pimpblelet by finish.","timestamp":"2026-01-22T02:58:19Z","url":"https://www.youtube.com/watch?v=T919vescT1o"}],"fp":"87b51dbb1d25","at":"2026-07-15T17:42:10.431Z"}