{"url":"https://www.youtube.com/watch?v=u9e6riDtYYQ","picks":[{"source":"Greedo Plays MMA","domain":"mma","pick":"Brad Tavares","opponent":"Robert Bryce","directness":"explicit","confidence":1,"quote":"I have no doubt in my mind Tvarez will not be Robert Bryce.","timestamp":"2025-09-04T19:00:53Z","url":"https://www.youtube.com/watch?v=u9e6riDtYYQ"},{"source":"Greedo Plays MMA","domain":"mma","pick":"William Gomez","opponent":"Robert Hula","directness":"explicit","confidence":0.9,"quote":"I just I don't expect William Gomez to lose at home.","timestamp":"2025-09-04T19:00:53Z","url":"https://www.youtube.com/watch?v=u9e6riDtYYQ"},{"source":"Greedo Plays MMA","domain":"mma","pick":"Marcin Tybura","opponent":"Ante Delija","directness":"explicit","confidence":0.8,"quote":"Marine Tybora money lion's all I want here.","timestamp":"2025-09-04T19:00:53Z","url":"https://www.youtube.com/watch?v=u9e6riDtYYQ"},{"source":"Greedo Plays MMA","domain":"mma","pick":"Modestas Bukauskas","opponent":"Paul Craig","directness":"explicit","confidence":0.8,"quote":"I fully expect Picowskis to knock this guy out.","timestamp":"2025-09-04T19:00:53Z","url":"https://www.youtube.com/watch?v=u9e6riDtYYQ"},{"source":"Greedo Plays MMA","domain":"mma","pick":"Mauricio Ruffy","opponent":"Benoit Saint Denis","directness":"explicit","confidence":0.9,"quote":"I'm going Mauricio Huffy to knock out Benois.","timestamp":"2025-09-04T19:00:53Z","url":"https://www.youtube.com/watch?v=u9e6riDtYYQ"},{"source":"Greedo Plays MMA","domain":"mma","pick":"Nassourdine Imavov","opponent":"Caio Borralho","directness":"explicit","confidence":0.8,"quote":"Give me an A MV to win the main event against Cowboy Ohio.","timestamp":"2025-09-04T19:00:53Z","url":"https://www.youtube.com/watch?v=u9e6riDtYYQ"}],"fp":"87b51dbb1d25","at":"2026-07-15T21:53:29.588Z"}