{"url":"https://www.youtube.com/watch?v=veTLu13loEc","picks":[{"source":"Behind the Lines News","domain":"mma","pick":"Carlos Ulberg","opponent":"Jiri Prochazka","directness":"implicit","confidence":1,"quote":"He turned one gifted second into UFC gold with that ridiculous power of his. And once that knee heals up, try to stop me. The whole division is going to have a very real problem on its hands.","timestamp":"2026-04-12T06:21:12Z","url":"https://www.youtube.com/watch?v=veTLu13loEc"}],"fp":"87b51dbb1d25","at":"2026-07-15T18:00:13.357Z"}