{"url":"https://www.youtube.com/watch?v=wdcvtQjWdrM","picks":[{"source":"Uselyis","domain":"mma","pick":"Kai Kamaka","opponent":"Dakota Hope","directness":"explicit","confidence":0.2,"quote":"The pick is going to be Kai Kamaka low confidence.","timestamp":"2026-04-03T22:42:31Z","url":"https://www.youtube.com/watch?v=wdcvtQjWdrM"},{"source":"Uselyis","domain":"mma","pick":"Daiane Barbosa","opponent":"Melissa Gatto","directness":"explicit","confidence":0.8,"quote":"I'm going to go Barbosa money line minus 134.","timestamp":"2026-04-03T22:42:31Z","url":"https://www.youtube.com/watch?v=wdcvtQjWdrM"},{"source":"Uselyis","domain":"mma","pick":"Azamat Bekoev","opponent":"Tresean Gore","directness":"explicit","confidence":0.9,"quote":"Give me Bekoev by KO plus 135.","timestamp":"2026-04-03T22:42:31Z","url":"https://www.youtube.com/watch?v=wdcvtQjWdrM"},{"source":"Uselyis","domain":"mma","pick":"Elise Reed","opponent":"Hailey Cowan","directness":"explicit","confidence":0.2,"quote":"I'm going to go Elise low confidence.","timestamp":"2026-04-03T22:42:31Z","url":"https://www.youtube.com/watch?v=wdcvtQjWdrM"},{"source":"Uselyis","domain":"mma","pick":"Lando Vannata","opponent":"Terrance McKinney","directness":"explicit","confidence":0.2,"quote":"Give me Lando Vannata to get this job done. Very low confidence.","timestamp":"2026-04-03T22:42:31Z","url":"https://www.youtube.com/watch?v=wdcvtQjWdrM"},{"source":"Uselyis","domain":"mma","pick":"Alessandro Costa","opponent":"Stuart Niccol","directness":"explicit","confidence":0.9,"quote":"Give me Costa money line as a parlay piece minus 430.","timestamp":"2026-04-03T22:42:31Z","url":"https://www.youtube.com/watch?v=wdcvtQjWdrM"},{"source":"Uselyis","domain":"mma","pick":"Gilmore Pat","opponent":"Thomas Peterson","directness":"explicit","confidence":0.7,"quote":"Give me Pat money line minus 104.","timestamp":"2026-04-03T22:42:31Z","url":"https://www.youtube.com/watch?v=wdcvtQjWdrM"},{"source":"Uselyis","domain":"mma","pick":"Jose Delano","opponent":"Robert Bryczek","directness":"explicit","confidence":0.8,"quote":"Delano's going to be the pick.","timestamp":"2026-04-03T22:42:31Z","url":"https://www.youtube.com/watch?v=wdcvtQjWdrM"},{"source":"Uselyis","domain":"mma","pick":"Tommy McMillan","opponent":"Manolo Zucchini","directness":"explicit","confidence":0.9,"quote":"I'm going to go Tommy by sub minus 125.","timestamp":"2026-04-03T22:42:31Z","url":"https://www.youtube.com/watch?v=wdcvtQjWdrM"},{"source":"Uselyis","domain":"mma","pick":"Rafael Estevam","opponent":"Ethan Ewing","directness":"explicit","confidence":0.1,"quote":"The pick is going to be Rafael Estevam. Very low confidence.","timestamp":"2026-04-03T22:42:31Z","url":"https://www.youtube.com/watch?v=wdcvtQjWdrM"},{"source":"Uselyis","domain":"mma","pick":"Abdul Rakhman Yakayev","opponent":"Brent Primus","directness":"explicit","confidence":1,"quote":"I'm going to go Yakayev money line minus 2000.","timestamp":"2026-04-03T22:42:31Z","url":"https://www.youtube.com/watch?v=wdcvtQjWdrM"},{"source":"Uselyis","domain":"mma","pick":"Virna Jandiroba","opponent":"Tabitha Ricci","directness":"explicit","confidence":0.2,"quote":"The pick is going to be low confidence Virna Jandiroba.","timestamp":"2026-04-03T22:42:31Z","url":"https://www.youtube.com/watch?v=wdcvtQjWdrM"},{"source":"Uselyis","domain":"mma","pick":"Chris Duncan","opponent":"Renato Moicano","directness":"explicit","confidence":0.2,"quote":"I'm going Chris Duncan for the dub.","timestamp":"2026-04-03T22:42:31Z","url":"https://www.youtube.com/watch?v=wdcvtQjWdrM"}],"fp":"87b51dbb1d25","at":"2026-07-15T22:00:35.656Z"}