{"url":"https://www.youtube.com/watch?v=Y3wbAWJajPk","picks":[{"source":"Jonny Says Boxing","domain":"boxing","pick":"Basharat","opponent":"Garza","directness":"explicit","confidence":0.8,"quote":"I think Basherat gets the dub here against Garza.","timestamp":"2026-07-10T17:12:34Z","url":"https://www.youtube.com/watch?v=Y3wbAWJajPk"},{"source":"Jonny Says Boxing","domain":"boxing","pick":"Adrian Yanez","opponent":"Cody Garbrandt","directness":"explicit","confidence":0.9,"quote":"I like I like Yian here on the money line.","timestamp":"2026-07-10T17:12:34Z","url":"https://www.youtube.com/watch?v=Y3wbAWJajPk"},{"source":"Jonny Says Boxing","domain":"boxing","pick":"Lonnie Kavanaugh","opponent":"Brandon Royval","directness":"explicit","confidence":0.85,"quote":"I got Lonnie on the money line on this fight.","timestamp":"2026-07-10T17:12:34Z","url":"https://www.youtube.com/watch?v=Y3wbAWJajPk"},{"source":"Jonny Says Boxing","domain":"boxing","pick":"Mario Bautista","opponent":"Cory Sandhagen","directness":"explicit","confidence":0.8,"quote":"I like Mario here. I sniped Mario at the beginning of the week.","timestamp":"2026-07-10T17:12:34Z","url":"https://www.youtube.com/watch?v=Y3wbAWJajPk"},{"source":"Jonny Says Boxing","domain":"boxing","pick":"Paddy Pimblett","opponent":"Benoit Saint Denis","directness":"explicit","confidence":0.8,"quote":"I like Patty to beat Saint Deny. I think Patty's wrestling I think it's going to be enough","timestamp":"2026-07-10T17:12:34Z","url":"https://www.youtube.com/watch?v=Y3wbAWJajPk"},{"source":"Jonny Says Boxing","domain":"boxing","pick":"Max Holloway","opponent":"Conor McGregor","directness":"explicit","confidence":0.85,"quote":"I'm cheering for I'm cheering for McGregor, but I'm picking Max.","timestamp":"2026-07-10T17:12:34Z","url":"https://www.youtube.com/watch?v=Y3wbAWJajPk"},{"source":"Jonny Says Boxing","domain":"boxing","pick":"Gable Steveson","opponent":"Alicia Ellison","directness":"explicit","confidence":0.95,"quote":"I'm taking Gable first round knockout. I'm going to add that to our parlay.","timestamp":"2026-07-10T17:12:34Z","url":"https://www.youtube.com/watch?v=Y3wbAWJajPk"},{"source":"Jonny Says Boxing","domain":"boxing","pick":"Alejandro Costa","opponent":"Cody Durden","directness":"explicit","confidence":0.8,"quote":"I'm going to take Aleandro Costa by knockout at plus 225.","timestamp":"2026-07-10T17:12:34Z","url":"https://www.youtube.com/watch?v=Y3wbAWJajPk"},{"source":"Jonny Says Boxing","domain":"boxing","pick":"Ryan Gandra","opponent":"Zachary Reese","directness":"explicit","confidence":0.8,"quote":"Gandra by knockout will take us from plus 1,000 to plus 2,000. I say we do it.","timestamp":"2026-07-10T17:12:34Z","url":"https://www.youtube.com/watch?v=Y3wbAWJajPk"},{"source":"Jonny Says Boxing","domain":"boxing","pick":"Luke Riley","opponent":"Kai Kamaka","directness":"explicit","confidence":0.75,"quote":"We'll take Luke Riley on the money line. We'll get some action.","timestamp":"2026-07-10T17:12:34Z","url":"https://www.youtube.com/watch?v=Y3wbAWJajPk"}],"fp":"9033f602cc53","at":"2026-07-14T22:38:43.042Z"}