{"url":"https://www.youtube.com/watch?v=Y4WFH8sgYqM","picks":[{"source":"MMA EXPERTS","domain":"mma","pick":"Melquizio Costa","opponent":"Dan Ige","directness":"explicit","confidence":0.9,"quote":"I really like the chances of Melquizio... I'm going to say Melquizio Costa does it.","timestamp":"2026-02-18T21:55:09Z","url":"https://www.youtube.com/watch?v=Y4WFH8sgYqM"},{"source":"MMA EXPERTS","domain":"mma","pick":"Ante Delija","opponent":"Sergey Spivak","directness":"explicit","confidence":0.9,"quote":"My call is Ante Delija... I'm going as far as to say I actually think he's going to knock Sergey Spivac out.","timestamp":"2026-02-18T21:55:09Z","url":"https://www.youtube.com/watch?v=Y4WFH8sgYqM"},{"source":"MMA EXPERTS","domain":"mma","pick":"Alden Coria","opponent":"Luis Gurule","directness":"explicit","confidence":0.95,"quote":"Alden Coria has so many advantages here. He's a lock of locks.","timestamp":"2026-02-18T21:55:09Z","url":"https://www.youtube.com/watch?v=Y4WFH8sgYqM"},{"source":"MMA EXPERTS","domain":"mma","pick":"Joselyne Edwards","opponent":"Nora Cornolle","directness":"explicit","confidence":0.85,"quote":"Yes, Joselyne Edwards should win.","timestamp":"2026-02-18T21:55:09Z","url":"https://www.youtube.com/watch?v=Y4WFH8sgYqM"},{"source":"MMA EXPERTS","domain":"mma","pick":"Carly Judice","opponent":"Juliana Miller","directness":"explicit","confidence":0.9,"quote":"Carly Judice should absolutely destroy Juliana Miller.","timestamp":"2026-02-18T21:55:09Z","url":"https://www.youtube.com/watch?v=Y4WFH8sgYqM"},{"source":"MMA EXPERTS","domain":"mma","pick":"Anthony Hernandez","opponent":"Sean Strickland","directness":"explicit","confidence":0.85,"quote":"Fluffy Hernandez in the main event is going to be a confident pick, too.","timestamp":"2026-02-18T21:55:09Z","url":"https://www.youtube.com/watch?v=Y4WFH8sgYqM"},{"source":"MMA EXPERTS","domain":"mma","pick":"Jean Paulo Lebasani","opponent":"Phil Rowe","directness":"explicit","confidence":0.8,"quote":"I think he can win. I think he shuts Phil Rowe down.","timestamp":"2026-02-18T21:55:09Z","url":"https://www.youtube.com/watch?v=Y4WFH8sgYqM"},{"source":"MMA EXPERTS","domain":"mma","pick":"Zach Reese","opponent":"Michel Pereira","directness":"explicit","confidence":0.7,"quote":"I'm going Zach Reese inside the distance.","timestamp":"2026-02-18T21:55:09Z","url":"https://www.youtube.com/watch?v=Y4WFH8sgYqM"},{"source":"MMA EXPERTS","domain":"mma","pick":"Ode Osbourne","opponent":"Alibi Idris","directness":"explicit","confidence":0.65,"quote":"I'm going to say that Ode Osbourne shocks him.","timestamp":"2026-02-18T21:55:09Z","url":"https://www.youtube.com/watch?v=Y4WFH8sgYqM"},{"source":"MMA EXPERTS","domain":"mma","pick":"Ramsey Brahim","opponent":"Punahele Soriano","directness":"implicit","confidence":0.75,"quote":"I think Ramsey Brahim should beat Soriano.","timestamp":"2026-02-18T21:55:09Z","url":"https://www.youtube.com/watch?v=Y4WFH8sgYqM"}],"fp":"87b51dbb1d25","at":"2026-07-15T05:14:11.872Z"}