{"url":"https://www.youtube.com/watch?v=YGxwZYoeTc8","picks":[{"source":"Kunath","domain":"mma","pick":"Diego Lopez","opponent":"Alexander Volkanovski","directness":"explicit","confidence":0.8,"quote":"Give me the challenger here. Give me Diego Lopez to win the rematch.","timestamp":"2026-01-27T23:47:57Z","url":"https://www.youtube.com/watch?v=YGxwZYoeTc8"},{"source":"Kunath","domain":"mma","pick":"Benoit Saint Denis","opponent":"Dan Hooker","directness":"explicit","confidence":0.7,"quote":"I will take Benois Santini to win.","timestamp":"2026-01-27T23:47:57Z","url":"https://www.youtube.com/watch?v=YGxwZYoeTc8"},{"source":"Kunath","domain":"mma","pick":"Mauricio Ruffy","opponent":"Rafael Fiziev","directness":"explicit","confidence":0.6,"quote":"I'm going to pick the guy with the more fun style... Give me Mauricio Huy to win this fight.","timestamp":"2026-01-27T23:47:57Z","url":"https://www.youtube.com/watch?v=YGxwZYoeTc8"},{"source":"Kunath","domain":"mma","pick":"Talson Tashada","opponent":"Tai Tuivasa","directness":"explicit","confidence":0.9,"quote":"Talson Tashada is definitely the play this week.","timestamp":"2026-01-27T23:47:57Z","url":"https://www.youtube.com/watch?v=YGxwZYoeTc8"},{"source":"Kunath","domain":"mma","pick":"Quillan Salkilld","opponent":"Jamie Mullarkey","directness":"explicit","confidence":0.9,"quote":"Give me Quill and Sal killed to extend the knockout streak to two.","timestamp":"2026-01-27T23:47:57Z","url":"https://www.youtube.com/watch?v=YGxwZYoeTc8"},{"source":"Kunath","domain":"mma","pick":"Junior Tafa","opponent":"Billy Goff","directness":"explicit","confidence":0.7,"quote":"I think he goes out there and springs the upset as the dog here.","timestamp":"2026-01-27T23:47:57Z","url":"https://www.youtube.com/watch?v=YGxwZYoeTc8"},{"source":"Kunath","domain":"mma","pick":"Cam Rowston","opponent":"Cody Brundage","directness":"explicit","confidence":0.8,"quote":"Give me Cam Rston to win this fight.","timestamp":"2026-01-27T23:47:57Z","url":"https://www.youtube.com/watch?v=YGxwZYoeTc8"},{"source":"Kunath","domain":"mma","pick":"Jacob Malkoun","opponent":"Torres Finny","directness":"explicit","confidence":0.8,"quote":"Give me Jacob Malcoun to win this fight.","timestamp":"2026-01-27T23:47:57Z","url":"https://www.youtube.com/watch?v=YGxwZYoeTc8"},{"source":"Kunath","domain":"mma","pick":"Oban Elliott","opponent":"Jonathan Miff","directness":"explicit","confidence":0.6,"quote":"I think Oon Elliott is going to make the infight adjustments better... Give me Oban Elliot by decision.","timestamp":"2026-01-27T23:47:57Z","url":"https://www.youtube.com/watch?v=YGxwZYoeTc8"},{"source":"Kunath","domain":"mma","pick":"Eha","opponent":"Khan Offley","directness":"explicit","confidence":0.7,"quote":"I'm going to take Eha to win.","timestamp":"2026-01-27T23:47:57Z","url":"https://www.youtube.com/watch?v=YGxwZYoeTc8"}],"fp":"87b51dbb1d25","at":"2026-07-15T05:08:40.801Z"}