{"url":"https://www.youtube.com/watch?v=z0HXAk6mex8","picks":[{"source":"Lucrative James","domain":"mma","pick":"Manel Cape","opponent":"Brandon Royval","directness":"explicit","confidence":0.9,"quote":"I'm going to go out there and I'm going to pick Manel Cape in this fight.","timestamp":"2025-12-07T06:26:30Z","url":"https://www.youtube.com/watch?v=z0HXAk6mex8"},{"source":"Lucrative James","domain":"mma","pick":"Kevin Vallejo","opponent":"Giga Jakarti","directness":"explicit","confidence":0.9,"quote":"I'm picking Kevin in this fight. I think he's going to go out there and I'm going to pick a KO outright.","timestamp":"2025-12-07T06:26:30Z","url":"https://www.youtube.com/watch?v=z0HXAk6mex8"},{"source":"Lucrative James","domain":"mma","pick":"Cesari Oleksiejczuk","opponent":"Caesar Almeida","directness":"explicit","confidence":0.7,"quote":"I will be picking not Michelle Alex, but Cesari Alex to get this win.","timestamp":"2025-12-07T06:26:30Z","url":"https://www.youtube.com/watch?v=z0HXAk6mex8"},{"source":"Lucrative James","domain":"mma","pick":"Morgan Charriere","opponent":"Melquizael Costa","directness":"explicit","confidence":0.5,"quote":"I'll pick him because of that. But this fight could go either way, boys.","timestamp":"2025-12-07T06:26:30Z","url":"https://www.youtube.com/watch?v=z0HXAk6mex8"},{"source":"Lucrative James","domain":"mma","pick":"Marcus Batche","opponent":"Kennedy Nzechukwu","directness":"explicit","confidence":0.6,"quote":"I will pick Marcus Batche to win this fight and I'll pick him to win it via submission.","timestamp":"2025-12-07T06:26:30Z","url":"https://www.youtube.com/watch?v=z0HXAk6mex8"},{"source":"Lucrative James","domain":"mma","pick":"Gillian Robertson","opponent":"Amanda Lemos","directness":"explicit","confidence":0.8,"quote":"My official prediction boys will be Gillian Robertson. Gets this one done inside the distance.","timestamp":"2025-12-07T06:26:30Z","url":"https://www.youtube.com/watch?v=z0HXAk6mex8"},{"source":"Lucrative James","domain":"mma","pick":"Yannis Ghemmouri","opponent":"Melik Baghdasaryan","directness":"explicit","confidence":0.8,"quote":"My prediction for this fight is going to be Yannis Ghemmouri to go out there and smash Melik Baghdasaryan on the mat.","timestamp":"2025-12-07T06:26:30Z","url":"https://www.youtube.com/watch?v=z0HXAk6mex8"},{"source":"Lucrative James","domain":"mma","pick":"Yaroslav Amosov","opponent":"Neil Magny","directness":"explicit","confidence":0.9,"quote":"I'm actually going to go out there and pick Yaroslav Amosov to submit him... Yaraslov Amosov winning this fight via submission.","timestamp":"2025-12-07T06:26:30Z","url":"https://www.youtube.com/watch?v=z0HXAk6mex8"},{"source":"Lucrative James","domain":"mma","pick":"Guilherme Pat","opponent":"Alan Fry","directness":"explicit","confidence":0.6,"quote":"I'll go with Pat for my official prediction.","timestamp":"2025-12-07T06:26:30Z","url":"https://www.youtube.com/watch?v=z0HXAk6mex8"},{"source":"Lucrative James","domain":"mma","pick":"Steven Asplund","opponent":"Shawn Sheriff","directness":"explicit","confidence":0.8,"quote":"I'm calling Asplund to get the win in this fight.","timestamp":"2025-12-07T06:26:30Z","url":"https://www.youtube.com/watch?v=z0HXAk6mex8"},{"source":"Lucrative James","domain":"mma","pick":"Tereza Bleda","opponent":"Jamie-Lyn Horth","directness":"explicit","confidence":0.8,"quote":"I'm picking her to win this fight fairly cleanly.","timestamp":"2025-12-07T06:26:30Z","url":"https://www.youtube.com/watch?v=z0HXAk6mex8"}],"fp":"87b51dbb1d25","at":"2026-07-15T05:26:48.030Z"}