[
  {
    "dateVerified": "2026-07-16",
    "market": "KXUFCFIGHT-26JUL18DUUSM-DU",
    "marketTitle": "Will Dricus Du Plessis win the Du Plessis vs Usman professional MMA fight scheduled for Jul 18, 2026?",
    "selection": "Dricus Du Plessis YES",
    "side": "yes",
    "price": 0.69,
    "contracts": 141.84,
    "maxPayout": 141.84,
    "totalCost": 100.00,
    "interfaceFee": 2.13,
    "effectiveChanceDisplayed": 0.71,
    "treatment": "taker",
    "source": "authenticated Kalshi UFC Quick Order ticket, $100, NOT submitted",
    "note": "contract price 0.69 equals the live yes_ask at collection time, independently confirming this is a taker buy at the ask rather than the post-fee effective chance"
  },
  {
    "dateVerified": "2026-07-16",
    "market": "KXUFCFIGHT-26JUL18MCMMON-MCM",
    "marketTitle": "Will Tommy McMillen win the McMillen vs Montes professional MMA fight scheduled for Jul 18, 2026?",
    "selection": "Tommy McMillen YES",
    "side": "yes",
    "price": 0.59,
    "contracts": 164.76,
    "maxPayout": 164.76,
    "totalCost": 100.00,
    "interfaceFee": 2.79,
    "effectiveChanceDisplayed": 0.61,
    "treatment": "taker",
    "source": "authenticated Kalshi UFC Quick Order ticket, $100, NOT submitted",
    "note": "nearest to 0.50, where the quadratic fee is largest — this example pins the rate's upper bound most tightly"
  },
  {
    "dateVerified": "2026-07-16",
    "market": "KXUFCFIGHT-26JUL18CORNIC-COR",
    "marketTitle": "Will Alden Coria win the Coria vs Nicoll professional MMA fight scheduled for Jul 18, 2026?",
    "selection": "Alden Coria YES",
    "side": "yes",
    "price": 0.89,
    "contracts": 111.49,
    "maxPayout": 111.49,
    "totalCost": 100.00,
    "interfaceFee": 0.77,
    "effectiveChanceDisplayed": 0.90,
    "treatment": "taker",
    "source": "authenticated Kalshi UFC Quick Order ticket, $100, NOT submitted",
    "note": "deep favourite, near the wing where a wrong rate hides — the fee here is a quarter of the 0.59 example despite a larger stake"
  }
]
